{
	"url": "https://www.novelupdates.com/series/refined-sunflower-and-the-little-priest/",
	"title": "Refined Sunflower and the Little Priest - Novel Updates",
	"image": "https://cdn.novelupdates.com/images/2019/03/1.jpg",
	"noveltype": "(CN)",
	"genre": "Comedy   Historical   Romance   Supernatural   Yaoi   ",
	"tags": "Cute Protagonist   Cute Story   Enemies Become Lovers   Handsome Male Lead   Human-Nonhuman Relationship   Multiple POV   Short Story   ",
	"rating": "(4.4 / 5.0, 183 votes)",
	"author": "Lu Tianyi   吕天逸   ",
	"year": "\n2015",
	"ranking": "#1969   #2955   #4024   #2527   #3521   ",
	"reviewcount": "20 Reviews sorted by",
	"description": "Once upon a time, there was a refined sunflower.\r\n\r\nHis favorite past-time was pretending to be a normal sunflower lurking in the sunflower patch. Whenever someone passes by in the middle of the night, the refined sunflower would point at the normal sunflowers in the field and say…\r\n\r\n“Ready–get set– stare at him!”\r\n\r\nOne day, he scared a certain little priest…\r\n\r\nAlthough the introduction seems very long, the story is actually just a few paragraphs…………_(:з”∠)_>"
}