{
	"url": "https://www.novelupdates.com/series/homemade-shaved-ice-of-a-highschool-girl-who-had-her-common-sense-altered/",
	"title": "Homemade Shaved Ice of a Highschool Girl who had her Common Sense Altered - Novel Updates",
	"image": "https://www.novelupdates.com/img/noimagefound.jpg",
	"noveltype": "(JP)",
	"genre": "Adult   Mature   ",
	"tags": "Brainwashing   Hypnotism   Mind Control   Oneshot   ",
	"rating": "(1.5 / 5.0, 11 votes)",
	"author": "Hakana Yoriyuki   儚依幸   ",
	"year": "\n2020",
	"ranking": "#2000   #2000   #10247   #11316   #12340   ",
	"reviewcount": "2 Reviews sorted by",
	"description": ">"
}