{
	"url": "https://www.novelupdates.com/series/the-men-around-me-are-weird/",
	"title": "The Men Around Me Are Weird - Novel Updates",
	"image": "https://www.novelupdates.com/img/noimagefound.jpg",
	"noveltype": "(CN)",
	"genre": "Adult   Drama   Fantasy   Harem   Mature   Romance   School Life   Smut   ",
	"tags": "Beautiful Female Lead   Character Growth   Dense Protagonist   Female Protagonist   First-time Interc**rse   Forced into a Relationship   Handsome Male Lead   Love Rivals   Modern Day   Multiple Protagonists   Naive Protagonist   Possessive Characters   Reverse Harem   R*pe   ",
	"rating": "(2.6 / 5.0, 24 votes)",
	"author": "淡画书墨   ",
	"year": "\n2020",
	"ranking": "#1722   #2311   #7953   #4496   #8238   ",
	"reviewcount": "1 Review sorted by",
	"description": "This is a story where everyone I know has been reborn, but I am the only one who has not been reborn.\r\n\r\nAfter waking up, Wang Wenwen felt that the men around her became a little strange. \r\n\r\nThe neighbor brother looked guilty and had love in his eyes; \r\n\r\nThe domineering boy at the same table aggressively pursued her, flirted with her and hated the neighbor brother; \r\n\r\nThe senior gentleman said softly that he would tutor her; \r\n\r\nThen there was this unknown president who said that she must marry him after she is twenty! \r\n\r\nhmmmm? \r\n\r\nBut she had a normal relationship with them before. Don't they all have a mental illness?>"
}