{
	"url": "https://www.novelupdates.com/series/what-so-you-wanna-cancel-the-engagement-ah-whatever/",
	"title": "What, So You Wanna Cancel The Engagement? Ah, whatever. - Novel Updates",
	"image": "https://www.novelupdates.com/img/noimagefound.jpg",
	"noveltype": "(JP)",
	"genre": "Comedy   Fantasy   Romance   Shoujo   ",
	"tags": "Broken Engagement   European Ambience   Female Protagonist   Nobles   ",
	"rating": "(2.3 / 5.0, 3 votes)",
	"author": "Ichouka   銀杏鹿   ",
	"year": "\n2021",
	"ranking": "#2000   #2000   #11735   #13810   #12970   ",
	"reviewcount": "No Reviews",
	"description": ">"
}