{
	"url": "https://www.novelupdates.com/series/winter-swan/",
	"title": "Winter Swan - Novel Updates",
	"image": "https://cdn.novelupdates.com/images/2019/09/Winter-Swan.jpg",
	"noveltype": "(KR)",
	"genre": "Josei   Psychological   Romance   School Life   ",
	"tags": "Abusive Characters   Adopted Protagonist   Bullying   Cruel Characters   Discrimination   Female Protagonist   Love Interest Falls in Love First   Obsessive Love   Racism   Twisted Personality   ",
	"rating": "(2.6 / 5.0, 19 votes)",
	"author": "Eun Jiyun   ",
	"year": "\nN/A",
	"ranking": "#3567   #2000   #9512   #11077   #10685   ",
	"reviewcount": "4 Reviews sorted by",
	"description": "A nordic romance that burns up coldly!\r\n'You and I are similar, don't you know? Amidst the foxes, we are two wolves who are bleeding from an injury.\r\n\r\nThe frozen capital of Norway, Oslo. Silye, an asian who have been discriminated and bullied just because of her race, decides to escape this frozen hell by jumping off the school building but is saved by being caught by the 'Emperor' of the school. This wasn't a good news. This was a nightmare on its own.>"
}