{
	"url": "https://www.novelupdates.com/series/journey-to-seek-past-reincarnations-the-fleeting-time-turns/",
	"title": "Journey to Seek Past Reincarnations (The Fleeting Time Turns) - Novel Updates",
	"image": "https://cdn.novelupdates.com/images/2015/12/JTSPRTFTT.jpg",
	"noveltype": "N/A",
	"genre": "Adventure   Sci-fi   Shoujo   Supernatural   ",
	"tags": "Amnesia   Devoted Love Interests   Female Protagonist   Multiple Reincarnated Individuals   Reincarnation   Reverse Harem   Time Travel   Vampires   ",
	"rating": "(3.2 / 5.0, 11 votes)",
	"author": "Vivibear   ",
	"year": "\n2007",
	"ranking": "#2000   #2000   #13204   #13807   #13025   ",
	"reviewcount": "No Reviews",
	"description": ">"
}