{
	"url": "https://www.novelupdates.com/series/homebody-fairy/",
	"title": "Homebody Fairy - Novel Updates",
	"image": "https://cdn.novelupdates.com/images/2018/09/Homebody-Fairy.jpg",
	"noveltype": "(CN)",
	"genre": "Fantasy   Romance   ",
	"tags": "Female Protagonist   ",
	"rating": "(2.7 / 5.0, 9 votes)",
	"author": "Zhou Yi   周祎   苏辜   ",
	"year": "\n2017",
	"ranking": "#2000   #2000   #12233   #10660   #10844   ",
	"reviewcount": "No Reviews",
	"description": "Xie Linlin, a little home fairy in heaven, recently got an impossible mission: to persuade their lazy emperor to give up his unhealthy habit of not leaving his living quarters.>"
}