{
	"url": "https://www.novelupdates.com/series/i-was-born-in-the-underworld/",
	"title": "I Was Born In The Underworld - Novel Updates",
	"image": "https://cdn.novelupdates.com/images/2021/03/I-Was-Born-In-The-Underworld.jpg",
	"noveltype": "(CN)",
	"genre": "Action   Fantasy   Mature   Shounen   Supernatural   Tragedy   ",
	"tags": "Apocalypse   Army   Cold Protagonist   Confident Protagonist   Demon Lord   Demons   Depictions of Cruelty   Evil Protagonist   Male Protagonist   Post-apocalyptic   Pragmatic Protagonist   Previous Life Talent   Proactive Protagonist   Protagonist Strong from the Start   Ruthless Protagonist   Second Chance   Selfish Protagonist   Twisted Personality   Zombies   ",
	"rating": "(3.8 / 5.0, 13 votes)",
	"author": "Justice Di   正义迪   ",
	"year": "\nN/A",
	"ranking": "#6970   #2000   #9952   #4539   #10512   ",
	"reviewcount": "2 Reviews sorted by",
	"description": "Ten years in the last days, like drinking cold ice.\r\nDark plagues come, before ancient fans return to the last days, the king who sees through the heart of indifference will completely subvert the world!>"
}