{
	"url": "https://www.novelupdates.com/series/the-rise-of-otaku/",
	"title": "The Rise of Otaku - Novel Updates",
	"image": "https://cdn.novelupdates.com/images/2019/04/The-Rise-of-Otaku.jpg",
	"noveltype": "(CN)",
	"genre": "Adventure   Shounen   Slice of Life   ",
	"tags": "Adventurers   Amusement Park   Anti-social Protagonist   Cheats   Chuunibyou   Dolls/Puppets   Farming   Game Elements   Imaginary Friend   Lazy Protagonist   Living Alone   Low-key Protagonist   Male Protagonist   Modern Day   Naive Protagonist   Neet   Otaku   Pets   ",
	"rating": "(4.1 / 5.0, 98 votes)",
	"author": "壶山小农   ",
	"year": "\nN/A",
	"ranking": "#6970   #2000   #2463   #6614   #5044   ",
	"reviewcount": "15 Reviews sorted by",
	"description": "Zhou Yu, a reclusive otaku who did not like to go out of his house, was one day forced out of his house by a series of unexpected events.>"
}