{
	"url": "https://www.novelupdates.com/series/legend-of-the-swordking/",
	"title": "Legend of the Swordking - Novel Updates",
	"image": "https://cdn.novelupdates.com/images/2017/05/Legend-of-the-Swordking.jpg",
	"noveltype": "(CN)",
	"genre": "Action   Martial Arts   School Life   Xuanhuan   ",
	"tags": "Cultivation   Male Protagonist   Romantic Subplot   Sword Wielder   ",
	"rating": "(4.0 / 5.0, 13 votes)",
	"author": "Shi Luo Ye   失落叶   ",
	"year": "\n2016",
	"ranking": "#2000   #2000   #10416   #7244   #10698   ",
	"reviewcount": "2 Reviews sorted by",
	"description": "The sword’s edge dictates: he is unrivaled under heaven.\n\nA youth whose failure to awaken resulted in crippled meridians and broken cultivation endures scorn and mocking to enter the Ten Thousand Spirit Academy as the lowliest external student.\n\nHowever, with a fortunate encounter, his spirit meridians are reborn. He who possesses a deep foundation will step by step raise his name above the academy, influence the entire northern region, and with a sword in hand become unstoppable across the DragonSpirit Continent.>"
}