{
	"url": "https://www.novelupdates.com/series/blazblue/",
	"title": "BlazBlue - Novel Updates",
	"image": "https://cdn.novelupdates.com/images/2015/11/BlazBlue_CalamityTrigger_Cover.jpg",
	"noveltype": "(JP)",
	"genre": "Action   Adventure   Fantasy   Seinen   ",
	"tags": "Based on a Video Game   ",
	"rating": "(3.4 / 5.0, 7 votes)",
	"author": "Komao Mako   MORI Toshimichi   ",
	"year": "\n2013",
	"ranking": "#2000   #2000   #13349   #13807   #12898   ",
	"reviewcount": "1 Review sorted by",
	"description": "AD 2199. The world is covered in seithr and mankind is forced to live in Hierarchical cities, ascending constructions similar to towers.\n\nThe 13th Hierarchical City of Kagutsuchi has been infiltrated by a man with the most bounty in the world. He is Ragna the Bloodedge, the ‘Grim Reaper’, a man who possesses the Azure Grimoire. Thus, the wheel of fate begins to turn.\n\n“Restriction 666 released, Dimensional Interference Field deployed! BlazBlue, activate!”\n\nThe popular fighting game BlazBlue’s first installment, Calamity Trigger. The new legend starts here!\n\nThe first 2 novels tell the story of Calamity Trigger while the final 2 tell the story of Continuum Shift.>"
}