{
	"url": "https://www.novelupdates.com/series/the-strongest-hokage/",
	"title": "The Strongest Hokage - Novel Updates",
	"image": "https://cdn.novelupdates.com/images/2017/10/Cover.jpg",
	"noveltype": "(CN)",
	"genre": "Action   Adventure   Fantasy   Martial Arts   Supernatural   Tragedy   ",
	"tags": "Academy   Age Progression   Beautiful Female Lead   Bloodlines   Body Tempering   Bullying   Cheats   Cultivation   Discrimination   Eye Powers   Fanfiction   Fast Cultivation   Fast Learner   Handsome Male Lead   Harsh Training   Male Protagonist   Mature Protagonist   Ninjas   Overpowered Protagonist   Romantic Subplot   Ruthless Protagonist   Special Abilities   Sudden Strength Gain   Unique Cultivation Technique   Weak to Strong   ",
	"rating": "(3.1 / 5.0, 234 votes)",
	"author": "Ye Nan Ting Feng   夜南听风   ",
	"year": "\n2016",
	"ranking": "#387   #1217   #488   #815   #2534   ",
	"reviewcount": "16 Reviews sorted by",
	"description": "The Gura Gura no Mi is known as the strongest fruit in the world of one piece.\n\nIn Naruto world, the blood limit would grant the strongest power for those ninjas. But what if the Gura Gura no Mi is found in the world of Naruto And after it is eaten it will be like a blood limit power.\n\nWell, the MC just took that Fruit.\n\nThis story begins before the second Ninja war by two years.>"
}