{
	"url": "https://www.novelupdates.com/series/i-dont-want-to-go-against-the-sky/",
	"title": "I Don’t Want To Go Against The Sky - Novel Updates",
	"image": "https://cdn.novelupdates.com/images/2020/01/82C4FF55-52B6-406F-A948-D4F9119E4B9A.jpeg",
	"noveltype": "(CN)",
	"genre": "Action   Comedy   Fantasy   Martial Arts   Xuanhuan   ",
	"tags": "Arranged Marriage   Arrogant Characters   Beautiful Female Lead   Calm Protagonist   Cheats   Cultivation   Destiny   Doting Parents   Dragons   Evil Gods   Famous Parents   Fast Cultivation   Game Elements   Gate to Another World   God Protagonist   Handsome Male Lead   Late Romance   Lazy Protagonist   Level System   Lucky Protagonist   Male Protagonist   Misunderstandings   Overpowered Protagonist   Parody   Pets   Pregnancy   Ruthless Protagonist   Sect Development   Servants   Shameless Protagonist   Skill Assimilation   System Administrator   Transmigration   Transported to Another World   Wars   Weak to Strong   ",
	"rating": "(3.4 / 5.0, 77 votes)",
	"author": "Xin Feng   新丰   ",
	"year": "\n2018",
	"ranking": "#6970   #6207   #3476   #2012   #5882   ",
	"reviewcount": "16 Reviews sorted by",
	"description": "When I became a rich young master, I had to enjoy it.\r\n\r\nTraining? No!\r\n\r\nThat is so boring.\r\n\r\nI have a system, no need for training.\r\n\r\nAre you hungry? Come, I will treat you with some food at a luxurious restaurant.\r\n\r\nWhat a poor homeless. Come, I will give you a house.\r\n\r\nI, Lin Fan am a good person.>"
}