{
	"id": "1zgvJgjxnHXZ4uk",
	"json": "{\"id\":\"1zgvJgjxnHXZ4uk\",\"url\":\"https://www.novelupdates.com/series/my-castle-my-castellan/\",\"loadedUrl\":\"https://www.novelupdates.com/series/my-castle-my-castellan/\",\"uniqueKey\":\"https://www.novelupdates.com/series/my-castle-my-castellan\",\"method\":\"GET\",\"noRetry\":false,\"retryCount\":0,\"errorMessages\":[],\"headers\":{},\"userData\":{\"label\":\"detail\"},\"handledAt\":\"2022-10-08T10:24:41.581Z\"}",
	"method": "GET",
	"orderNo": null,
	"retryCount": 0,
	"uniqueKey": "https://www.novelupdates.com/series/my-castle-my-castellan",
	"url": "https://www.novelupdates.com/series/my-castle-my-castellan/"
}