{
	"id": "3EVVkofAzzJqfkc",
	"json": "{\"id\":\"3EVVkofAzzJqfkc\",\"url\":\"https://www.novelupdates.com/series/going-against-the-wind/\",\"loadedUrl\":\"https://www.novelupdates.com/series/going-against-the-wind/\",\"uniqueKey\":\"https://www.novelupdates.com/series/going-against-the-wind\",\"method\":\"GET\",\"noRetry\":false,\"retryCount\":0,\"errorMessages\":[],\"headers\":{},\"userData\":{\"label\":\"detail\"},\"handledAt\":\"2022-10-08T10:28:15.810Z\"}",
	"method": "GET",
	"orderNo": null,
	"retryCount": 0,
	"uniqueKey": "https://www.novelupdates.com/series/going-against-the-wind",
	"url": "https://www.novelupdates.com/series/going-against-the-wind/"
}