{
	"id": "ARhaZispSnNv0FO",
	"json": "{\"id\":\"ARhaZispSnNv0FO\",\"url\":\"https://www.novelupdates.com/series/the-tragedy-of-the-villainess/\",\"loadedUrl\":\"https://www.novelupdates.com/series/the-tragedy-of-the-villainess/\",\"uniqueKey\":\"https://www.novelupdates.com/series/the-tragedy-of-the-villainess\",\"method\":\"GET\",\"noRetry\":false,\"retryCount\":0,\"errorMessages\":[],\"headers\":{},\"userData\":{\"label\":\"detail\"},\"handledAt\":\"2022-10-08T10:23:49.011Z\"}",
	"method": "GET",
	"orderNo": null,
	"retryCount": 0,
	"uniqueKey": "https://www.novelupdates.com/series/the-tragedy-of-the-villainess",
	"url": "https://www.novelupdates.com/series/the-tragedy-of-the-villainess/"
}