{
	"id": "CEc3mGJRLyFOuYQ",
	"json": "{\"id\":\"CEc3mGJRLyFOuYQ\",\"url\":\"https://www.novelupdates.com/series/god-of-war/\",\"loadedUrl\":\"https://www.novelupdates.com/series/god-of-war/\",\"uniqueKey\":\"https://www.novelupdates.com/series/god-of-war\",\"method\":\"GET\",\"noRetry\":false,\"retryCount\":0,\"errorMessages\":[],\"headers\":{},\"userData\":{\"label\":\"detail\"},\"handledAt\":\"2022-10-08T10:27:43.645Z\"}",
	"method": "GET",
	"orderNo": null,
	"retryCount": 0,
	"uniqueKey": "https://www.novelupdates.com/series/god-of-war",
	"url": "https://www.novelupdates.com/series/god-of-war/"
}