{
	"id": "JLTyzpr6Duq7jkG",
	"json": "{\"id\":\"JLTyzpr6Duq7jkG\",\"url\":\"https://www.novelupdates.com/series/everyone-thinks-that-i-like-him/\",\"loadedUrl\":\"https://www.novelupdates.com/series/everyone-thinks-that-i-like-him/\",\"uniqueKey\":\"https://www.novelupdates.com/series/everyone-thinks-that-i-like-him\",\"method\":\"GET\",\"noRetry\":false,\"retryCount\":0,\"errorMessages\":[],\"headers\":{},\"userData\":{\"label\":\"detail\"},\"handledAt\":\"2022-10-08T10:23:03.669Z\"}",
	"method": "GET",
	"orderNo": null,
	"retryCount": 0,
	"uniqueKey": "https://www.novelupdates.com/series/everyone-thinks-that-i-like-him",
	"url": "https://www.novelupdates.com/series/everyone-thinks-that-i-like-him/"
}