{
	"id": "K1M1orxPjR2b9Dl",
	"json": "{\"id\":\"K1M1orxPjR2b9Dl\",\"url\":\"https://www.novelupdates.com/series/fanatic-divine-cultivator/\",\"loadedUrl\":\"https://www.novelupdates.com/series/fanatic-divine-cultivator/\",\"uniqueKey\":\"https://www.novelupdates.com/series/fanatic-divine-cultivator\",\"method\":\"GET\",\"noRetry\":false,\"retryCount\":0,\"errorMessages\":[],\"headers\":{},\"userData\":{\"label\":\"detail\"},\"handledAt\":\"2022-10-08T10:26:34.713Z\"}",
	"method": "GET",
	"orderNo": null,
	"retryCount": 0,
	"uniqueKey": "https://www.novelupdates.com/series/fanatic-divine-cultivator",
	"url": "https://www.novelupdates.com/series/fanatic-divine-cultivator/"
}