{
	"id": "K7rPcpSh3N7ysLS",
	"json": "{\"id\":\"K7rPcpSh3N7ysLS\",\"url\":\"https://www.novelupdates.com/series/elixir-supplier/\",\"loadedUrl\":\"https://www.novelupdates.com/series/elixir-supplier/\",\"uniqueKey\":\"https://www.novelupdates.com/series/elixir-supplier\",\"method\":\"GET\",\"noRetry\":false,\"retryCount\":0,\"errorMessages\":[],\"headers\":{},\"userData\":{\"label\":\"detail\"},\"handledAt\":\"2022-10-08T10:27:57.401Z\"}",
	"method": "GET",
	"orderNo": null,
	"retryCount": 0,
	"uniqueKey": "https://www.novelupdates.com/series/elixir-supplier",
	"url": "https://www.novelupdates.com/series/elixir-supplier/"
}