{
	"id": "M8cb3aoGFIb10FB",
	"json": "{\"id\":\"M8cb3aoGFIb10FB\",\"url\":\"https://www.novelupdates.com/series/return-of-the-legendary-hunter/\",\"loadedUrl\":\"https://www.novelupdates.com/series/return-of-the-legendary-hunter/\",\"uniqueKey\":\"https://www.novelupdates.com/series/return-of-the-legendary-hunter\",\"method\":\"GET\",\"noRetry\":false,\"retryCount\":0,\"errorMessages\":[],\"headers\":{},\"userData\":{\"label\":\"detail\"},\"handledAt\":\"2022-10-08T10:22:02.137Z\"}",
	"method": "GET",
	"orderNo": null,
	"retryCount": 0,
	"uniqueKey": "https://www.novelupdates.com/series/return-of-the-legendary-hunter",
	"url": "https://www.novelupdates.com/series/return-of-the-legendary-hunter/"
}