{
	"id": "MGUqbxG0jhSnFnT",
	"json": "{\"id\":\"MGUqbxG0jhSnFnT\",\"url\":\"https://www.novelupdates.com/series/pride-and-sanctimony/\",\"loadedUrl\":\"https://www.novelupdates.com/series/pride-and-sanctimony/\",\"uniqueKey\":\"https://www.novelupdates.com/series/pride-and-sanctimony\",\"method\":\"GET\",\"noRetry\":false,\"retryCount\":0,\"errorMessages\":[],\"headers\":{},\"userData\":{\"label\":\"detail\"},\"handledAt\":\"2022-10-06T15:34:33.463Z\"}",
	"method": "GET",
	"orderNo": null,
	"retryCount": 0,
	"uniqueKey": "https://www.novelupdates.com/series/pride-and-sanctimony",
	"url": "https://www.novelupdates.com/series/pride-and-sanctimony/"
}