{
	"id": "MNLSfg3qauK2rIY",
	"json": "{\"id\":\"MNLSfg3qauK2rIY\",\"url\":\"https://www.novelupdates.com/series/hope-youve-been-well/\",\"loadedUrl\":\"https://www.novelupdates.com/series/hope-youve-been-well/\",\"uniqueKey\":\"https://www.novelupdates.com/series/hope-youve-been-well\",\"method\":\"GET\",\"noRetry\":false,\"retryCount\":0,\"errorMessages\":[],\"headers\":{},\"userData\":{\"label\":\"detail\"},\"handledAt\":\"2022-10-06T15:36:17.100Z\"}",
	"method": "GET",
	"orderNo": null,
	"retryCount": 0,
	"uniqueKey": "https://www.novelupdates.com/series/hope-youve-been-well",
	"url": "https://www.novelupdates.com/series/hope-youve-been-well/"
}