{
	"id": "PPUeD5qiVIatIfA",
	"json": "{\"id\":\"PPUeD5qiVIatIfA\",\"url\":\"https://www.novelupdates.com/series/star-charts-edge/\",\"loadedUrl\":\"https://www.novelupdates.com/series/star-charts-edge/\",\"uniqueKey\":\"https://www.novelupdates.com/series/star-charts-edge\",\"method\":\"GET\",\"noRetry\":false,\"retryCount\":0,\"errorMessages\":[],\"headers\":{},\"userData\":{\"label\":\"detail\"},\"handledAt\":\"2022-10-08T10:24:16.370Z\"}",
	"method": "GET",
	"orderNo": null,
	"retryCount": 0,
	"uniqueKey": "https://www.novelupdates.com/series/star-charts-edge",
	"url": "https://www.novelupdates.com/series/star-charts-edge/"
}