{
	"id": "q9rVsb0UsHqSb3a",
	"json": "{\"id\":\"q9rVsb0UsHqSb3a\",\"url\":\"https://www.novelupdates.com/series/overlord-wn/\",\"loadedUrl\":\"https://www.novelupdates.com/series/overlord-wn/\",\"uniqueKey\":\"https://www.novelupdates.com/series/overlord-wn\",\"method\":\"GET\",\"noRetry\":false,\"retryCount\":0,\"errorMessages\":[],\"headers\":{},\"userData\":{\"label\":\"detail\"},\"handledAt\":\"2022-10-08T10:28:00.576Z\"}",
	"method": "GET",
	"orderNo": null,
	"retryCount": 0,
	"uniqueKey": "https://www.novelupdates.com/series/overlord-wn",
	"url": "https://www.novelupdates.com/series/overlord-wn/"
}