{
	"id": "QbEFKNhZ4M1tE44",
	"json": "{\"id\":\"QbEFKNhZ4M1tE44\",\"url\":\"https://www.novelupdates.com/series/how-hurtful-of-the-maple-leaves/\",\"loadedUrl\":\"https://www.novelupdates.com/series/how-hurtful-of-the-maple-leaves/\",\"uniqueKey\":\"https://www.novelupdates.com/series/how-hurtful-of-the-maple-leaves\",\"method\":\"GET\",\"noRetry\":false,\"retryCount\":0,\"errorMessages\":[],\"headers\":{},\"userData\":{\"label\":\"detail\"},\"handledAt\":\"2022-10-08T10:28:33.070Z\"}",
	"method": "GET",
	"orderNo": null,
	"retryCount": 0,
	"uniqueKey": "https://www.novelupdates.com/series/how-hurtful-of-the-maple-leaves",
	"url": "https://www.novelupdates.com/series/how-hurtful-of-the-maple-leaves/"
}