{
	"id": "qULnl4BfjA9FmMz",
	"json": "{\"id\":\"qULnl4BfjA9FmMz\",\"url\":\"https://www.novelupdates.com/series/falling-leaves-without-trace/\",\"loadedUrl\":\"https://www.novelupdates.com/series/falling-leaves-without-trace/\",\"uniqueKey\":\"https://www.novelupdates.com/series/falling-leaves-without-trace\",\"method\":\"GET\",\"noRetry\":false,\"retryCount\":0,\"errorMessages\":[],\"headers\":{},\"userData\":{\"label\":\"detail\"},\"handledAt\":\"2022-10-08T10:28:25.339Z\"}",
	"method": "GET",
	"orderNo": null,
	"retryCount": 0,
	"uniqueKey": "https://www.novelupdates.com/series/falling-leaves-without-trace",
	"url": "https://www.novelupdates.com/series/falling-leaves-without-trace/"
}