{
	"id": "Rl0OGUtmld9Yk7l",
	"json": "{\"id\":\"Rl0OGUtmld9Yk7l\",\"url\":\"https://www.novelupdates.com/series/transmigrating-with-a-cleaver/\",\"loadedUrl\":\"https://www.novelupdates.com/series/transmigrating-with-a-cleaver/\",\"uniqueKey\":\"https://www.novelupdates.com/series/transmigrating-with-a-cleaver\",\"method\":\"GET\",\"noRetry\":false,\"retryCount\":0,\"errorMessages\":[],\"headers\":{},\"userData\":{\"label\":\"detail\"},\"handledAt\":\"2022-10-08T10:29:14.103Z\"}",
	"method": "GET",
	"orderNo": null,
	"retryCount": 0,
	"uniqueKey": "https://www.novelupdates.com/series/transmigrating-with-a-cleaver",
	"url": "https://www.novelupdates.com/series/transmigrating-with-a-cleaver/"
}