{
	"id": "RW9ITxDiCDMzOsM",
	"json": "{\"id\":\"RW9ITxDiCDMzOsM\",\"url\":\"https://www.novelupdates.com/series/my-mr-soldier/\",\"loadedUrl\":\"https://www.novelupdates.com/series/my-mr-soldier/\",\"uniqueKey\":\"https://www.novelupdates.com/series/my-mr-soldier\",\"method\":\"GET\",\"noRetry\":false,\"retryCount\":0,\"errorMessages\":[],\"headers\":{},\"userData\":{\"label\":\"detail\"},\"handledAt\":\"2022-10-06T15:36:04.219Z\"}",
	"method": "GET",
	"orderNo": null,
	"retryCount": 0,
	"uniqueKey": "https://www.novelupdates.com/series/my-mr-soldier",
	"url": "https://www.novelupdates.com/series/my-mr-soldier/"
}