{
	"id": "VsakMZIBUssmly9",
	"json": "{\"id\":\"VsakMZIBUssmly9\",\"url\":\"https://www.novelupdates.com/series/asylum-live-broadcast-room/\",\"loadedUrl\":\"https://www.novelupdates.com/series/asylum-live-broadcast-room/\",\"uniqueKey\":\"https://www.novelupdates.com/series/asylum-live-broadcast-room\",\"method\":\"GET\",\"noRetry\":false,\"retryCount\":0,\"errorMessages\":[],\"headers\":{},\"userData\":{\"label\":\"detail\"},\"handledAt\":\"2022-10-06T15:37:23.219Z\"}",
	"method": "GET",
	"orderNo": null,
	"retryCount": 0,
	"uniqueKey": "https://www.novelupdates.com/series/asylum-live-broadcast-room",
	"url": "https://www.novelupdates.com/series/asylum-live-broadcast-room/"
}