{
	"id": "wAHVIQzLX0okiNR",
	"json": "{\"id\":\"wAHVIQzLX0okiNR\",\"url\":\"https://www.novelupdates.com/series/kitchen-xiuzhen/\",\"loadedUrl\":\"https://www.novelupdates.com/series/kitchen-xiuzhen/\",\"uniqueKey\":\"https://www.novelupdates.com/series/kitchen-xiuzhen\",\"method\":\"GET\",\"noRetry\":false,\"retryCount\":0,\"errorMessages\":[],\"headers\":{},\"userData\":{\"label\":\"detail\"},\"handledAt\":\"2022-10-06T15:34:23.921Z\"}",
	"method": "GET",
	"orderNo": null,
	"retryCount": 0,
	"uniqueKey": "https://www.novelupdates.com/series/kitchen-xiuzhen",
	"url": "https://www.novelupdates.com/series/kitchen-xiuzhen/"
}